jrmlops/__init__.py
jrmlops/__version__.py
jrmlops/data/life_expectancy.zip
jrmlops/data.py
jrmlops-0.1.3.dist-info/METADATA
jrmlops-0.1.3.dist-info/WHEEL
jrmlops-0.1.3.dist-info/RECORD
